Workbook

Sheet Client_Master
A1: Client_ID | B1: Legal_Name | C1: Entity_Type | D1: Country | E1: Region | F1: Business_Unit | G1: Ownership_Structure | H1: UBO_Identified | I1: PEP_Connection | J1: Adverse_Media | K1: Sanctions_Screening | L1: Last_Review_Date | N1: Legend
A2: CL0001 | B2: Maple Opportunities Fund LP | C2: Investment Fund | D2: Canada | E2: Canada | F2: Equities | G2: Complex | H2: N | I2: N | J2: None | K2: Clear | L2: 45020 | N2: Yellow row 2 = example only, delete it in Step 2.
A3: CL0002 | B3: Granite Teachers Pension Plan | C3: Pension Fund | D3: United States | E3: US | F3: Equities | G3: Simple | H3: Y | I3: N | J3: None | K3: Clear | L3: 45975 | N3: Columns C, E–K have dropdowns.
A4: CL0003 | B4: Redstone Opportunities Fund Ltd | C4: Investment Fund | D4: Japan | E4: APAC | F4: Equities | G4: Simple | H4: Y | I4: N | J4: None | K4: Clear | L4: 46293 | N4: Hover a header to see what it means.
A5: CL0004 | B5: Westmark Multi-Strategy Fund Ltd | C5: Investment Fund | D5: Canada | E5: Canada | F5: Equities | G5: Simple | H5: Y | I5: N | J5: None | K5: Clear | L5: 45334
A6: CL0005 | B6: Ironwood Equity Income Fund Ltd | C6: Investment Fund | D6: Canada | E6: Canada | F6: FX | G6: Simple | H6: Y | I6: N | J6: None | K6: Clear | L6: 45698
A7: CL0006 | B7: Clearview Securities Inc. | C7: Bank | D7: Canada | E7: Canada | F7: Equities | G7: Simple | H7: Y | I7: N | J7: None | K7: Clear | L7: 45387 | N7: =COUNTA(A2:A201) -> 200
A8: CL0007 | B8: Kingsway Partners LLC | C8: Corporation | D8: United States | E8: US | F8: Fixed Income | G8: Simple | H8: Y | I8: N | J8: None | K8: Clear | L8: 44881 | N8: =COUNTBLANK(L2:L201) -> 3
A9: CL0008 | B9: Cedar Credit Fund LP | C9: Investment Fund | D9: British Virgin Islands | E9: Offshore | F9: Fixed Income | G9: Complex | H9: Y | I9: N | J9: None | K9: Clear | L9: 45404 | N9: =COUNTBLANK(H2:H201) -> 2
A10: CL0009 | B10: Meridian Workers Pension Plan | C10: Pension Fund | D10: Australia | E10: APAC | F10: Equities | G10: Simple | H10: Y | I10: N | J10: None | K10: Clear | L10: 46183 | N10: =COUNTIF(K2:K201,"Potential Match") -> 6
A11: CL0010 | B11: Aurora Municipal Pension Plan | C11: Pension Fund | D11: Canada | E11: Canada | F11: Equities | G11: Simple | H11: Y | I11: N | J11: None | K11: Clear | L11: 45890 | N11: =COUNTIF(I2:I201,"Y") -> 10
A12: CL0011 | B12: Pinecrest Charitable Trust | C12: Trust | D12: Bermuda | E12: Offshore | F12: Fixed Income | G12: Complex | H12: Y | I12: N | J12: None | K12: Clear | L12: 45060 | N12: CL0003
A13: CL0012 | B13: Clearview Asset Management LLC | C13: Corporation | D13: United States | E13: US | F13: Equities | G13: Simple | H13: Y | I13: N | J13: None | K13: Clear | L13: 46134 | N13: CL0038
A14: CL0013 | B14: Westmark Opportunities Fund LP | C14: Investment Fund | D14: Canada | E14: Canada | F14: Equities | G14: Simple | H14: Y | I14: N | J14: None | K14: Clear | L14: 45536 | N14: CL0091
A15: CL0014 | B15: Aurora Employees Pension Plan | C15: Pension Fund | D15: Luxembourg | E15: Europe | F15: FX | G15: Simple | H15: Y | I15: N | J15: None | K15: Clear | L15: 45445 | N15: CL0120
A16: CL0015 | B16: Aurora Legacy Trust | C16: Trust | D16: Cayman Islands | E16: Offshore | F16: FX | G16: Complex | H16: Y | I16: N | J16: None | K16: Clear | L16: 45234
A17: CL0016 | B17: Atlas Global Macro Fund Ltd | C17: Investment Fund | D17: Ireland | E17: Europe | F17: Fixed Income | G17: Complex | H17: N | I17: Y | J17: None | K17: Clear | L17: 45540
A18: CL0017 | B18: Silverline Family Trust | C18: Trust | D18: United States | E18: US | F18: FX | G18: Complex | H18: Y | I18: N | J18: None | K18: Clear | L18: 44838
A19: CL0018 | B19: Harbour Trust Company LLC | C19: Bank | D19: United States | E19: US | F19: Fixed Income | G19: Complex | H19: Y | I19: N | J19: None | K19: Clear | L19: 46137
A20: CL0019 | B20: Brightwater Opportunities Fund LP | C20: Investment Fund | D20: Canada | E20: Canada | F20: Equities | G20: Complex | H20: N | I20: N | J20: Minor | K20: Clear | L20: 46055
A21: CL0020 | B21: North Opportunities Fund LP | C21: Investment Fund | D21: Bermuda | E21: Offshore | F21: Equities | G21: Complex | H21: Y | I21: N | J21: Minor | K21: Clear | L21: 45350
A22: CL0021 | B22: Ironwood Securities Inc. | C22: Bank | D22: Canada | E22: Canada | F22: Fixed Income | G22: Simple | H22: Y | I22: N | J22: None | K22: Clear | L22: 45893
A23: CL0022 | B23: Eastbay Multi-Strategy Fund LP | C23: Investment Fund | D23: United States | E23: US | F23: Equities | G23: Simple | H23: Y | I23: N | J23: None | K23: Clear | L23: 46102
A24: CL0023 | B24: Fairhaven Energy B.V. | C24: Corporation | D24: Netherlands | E24: Europe | F24: Equities | G24: Simple | H24: Y | I24: N | J24: Minor | K24: Clear | L24: 44921
A25: CL0024 | B25: North Opportunities Fund Ltd | C25: Investment Fund | D25: Netherlands | E25: Europe | F25: Fixed Income | G25: Complex | H25: Y | I25: N | J25: None | K25: Clear | L25: 45814
A26: CL0025 | B26: Meridian Trust Company LLC | C26: Bank | D26: United States | E26: US | F26: Equities | G26: Simple | H26: Y | I26: N | J26: None | K26: Clear | L26: 46209
A27: CL0026 | B27: Bluewater Holdings Inc. | C27: Corporation | D27: Canada | E27: Canada | F27: FX | G27: Simple | H27: Y | I27: N | J27: None | K27: Clear | L27: 45792
... A73: CL0072 | B73: Cedar Opportunities Fund Ltd | C73: Investment Fund | D73: Cayman Islands | E73: Offshore | F73: Fixed Income | G73: Complex | H73: Y | I73: N | J73: None | K73: Clear | L73: 46215
A74: CL0073 | B74: Bluewater Securities Inc. | C74: Bank | D74: Canada | E74: Canada | F74: Equities | G74: Simple | H74: Y | I74: N | J74: None | K74: Clear
A75: CL0074 | B75: Pinecrest Partners Inc. | C75: Corporation | D75: Canada | E75: Canada | F75: FX | G75: Simple | H75: Y | I75: N | J75: None | K75: Clear | L75: 45044
A76: CL0075 | B76: Silverline Employees Pension Plan | C76: Pension Fund | D76: Canada | E76: Canada | F76: Equities | G76: Simple | H76: Y | I76: N | J76: None | K76: Clear | L76: 44988
A77: CL0076 | B77: Meridian Opportunities Fund LP | C77: Investment Fund | D77: United States | E77: US | F77: Equities | G77: Simple | H77: Y | I77: N | J77: None | K77: Clear | L77: 45357
A78: CL0077 | B78: Ironwood Workers Pension Plan | C78: Pension Fund | D78: Canada | E78: Canada | F78: Fixed Income | G78: Simple | H78: Y | I78: N | J78: None | K78: Clear | L78: 44964
A79: CL0078 | B79: Summit Trust Company LLC | C79: Bank | D79: United States | E79: US | F79: Fixed Income | G79: Simple | H79: Y | I79: N | J79: None | K79: Clear | L79: 45690
A80: CL0079 | B80: Lakeshore Securities Ltd | C80: Bank | D80: British Virgin Islands | E80: Offshore | F80: Fixed Income | G80: Complex | H80: Y | I80: N | J80: None | K80: Clear | L80: 44847
A81: CL0080 | B81: Harbour Equity Income Fund Ltd | C81: Investment Fund | D81: United States | E81: US | F81: FX | G81: Complex | H81: N | I81: Y | J81: None | K81: Clear | L81: 45017
A82: CL0081 | B82: Aurora Bank Ltd | C82: Bank | D82: United Kingdom | E82: UK | F82: FX | G82: Simple | H82: Y | I82: N | J82: None | K82: Clear | L82: 45239
A83: CL0082 | B83: Westmark Legacy Trust | C83: Trust | D83: Canada | E83: Canada | F83: FX | G83: Complex | H83: Y | I83: N | J83: Minor | K83: Clear | L83: 45163
A84: CL0083 | B84: Oakridge Global Macro Fund Ltd | C84: Investment Fund | D84: United Kingdom | E84: UK | F84: Equities | G84: Complex | H84: Y | I84: N | J84: None | K84: Clear | L84: 45340
A85: CL0084 | B85: Pinecrest Multi-Strategy Fund Ltd | C85: Investment Fund | D85: Cayman Islands | E85: Offshore | F85: Fixed Income | G85: Complex | H85: Y | I85: N | J85: None | K85: Clear | L85: 46184
A86: CL0085 | B86: North Logistics LLC | C86: Corporation | D86: United States | E86: US | F86: FX | G86: Simple | H86: Y | I86: N | J86: None | K86: Clear | L86: 45804
... A92: CL0091 | B92: Redstone Securities Pte Ltd | C92: Corporation | D92: Singapore | E92: APAC | F92: Equities | G92: Simple | H92: Y | I92: N | J92: None | K92: Clear | L92: 45512
A93: CL0092 | B93: Oakridge Advisors S.à r.l. | C93: Corporation | D93: Luxembourg | E93: Europe | F93: FX | G93: Simple | H93: Y | I93: N | J93: None | K93: Clear
A94: CL0093 | B94: Atlas Bank Pte Ltd | C94: Bank | D94: Singapore | E94: APAC | F94: Fixed Income | G94: Simple | H94: Y | I94: N | J94: None | K94: Clear | L94: 46089
A95: CL0094 | B95: Clearview Resources Ltd | C95: Corporation | D95: United Kingdom | E95: UK | F95: Equities | G95: Simple | H95: Y | I95: N | J95: None | K95: Clear | L95: 45585
A96: CL0095 | B96: North Industries Ltd | C96: Corporation | D96: United Kingdom | E96: UK | F96: Equities | G96: Simple | H96: Y | I96: Y | J96: None | K96: Clear | L96: 45376
A97: CL0096 | B97: Oakridge Charitable Trust | C97: Trust | D97: Cayman Islands | E97: Offshore | F97: Equities | G97: Complex | H97: Y | I97: N | J97: None | K97: Potential Match | L97: 44886
A98: CL0097 | B98: Crescent Holdings LLC | C98: Corporation | D98: United States | E98: US | F98: Fixed Income | G98: Complex | H98: Y | I98: N | J98: None | K98: Clear | L98: 45873
A99: CL0098 | B99: Harbour Municipal Pension Plan | C99: Pension Fund | D99: United Kingdom | E99: UK | F99: Equities | G99: Simple | H99: Y | I99: N | J99: None | K99: Clear | L99: 45729
A100: CL0099 | B100: Stonebridge Investments S.à r.l. | C100: Corporation | D100: Luxembourg | E100: Europe | F100: FX | G100: Complex | H100: Y | I100: N | J100: None | K100: Clear | L100: 46258
A101: CL0100 | B101: Fairhaven Legacy Trust | C101: Trust | D101: British Virgin Islands | E101: Offshore | F101: Equities | G101: Complex | H101: Y | I101: N | J101: None | K101: Clear | L101: 45318
A102: CL0101 | B102: Brightwater Legacy Trust | C102: Trust | D102: Hong Kong | E102: APAC | F102: FX | G102: Complex | H102: Y | I102: N | J102: None | K102: Clear | L102: 46197
A103: CL0102 | B103: Eastbay Opportunities Fund LP | C103: Investment Fund | D103: Australia | E103: APAC | F103: Fixed Income | G103: Complex | H103: Y | I103: N | J103: None | K103: Clear | L103: 44994
A104: CL0103 | B104: North Holdings Ltd | C104: Corporation | D104: United Kingdom | E104: UK | F104: Equities | G104: Complex | H104: Y | I104: N | J104: None | K104: Potential Match | L104: 46253
A105: CL0104 | B105: Brightwater Bank Ltd | C105: Bank | D105: United Kingdom | E105: UK | F105: FX | G105: Complex | H105: Y | I105: N | J105: None | K105: Clear
A106: CL0105 | B106: Cedar Industries Pty Ltd | C106: Corporation | D106: Australia | E106: APAC | F106: FX | G106: Complex | H106: N | I106: N | J106: None | K106: Clear | L106: 46128
A107: CL0106 | B107: Granite Securities Ltd | C107: Corporation | D107: United Kingdom | E107: UK | F107: Equities | G107: Complex | H107: Y | I107: N | J107: None | K107: Clear | L107: 45588
A108: CL0107 | B108: Oakridge Employees Pension Plan | C108: Pension Fund | D108: Australia | E108: APAC | F108: Equities | G108: Simple | H108: Y | I108: N | J108: None | K108: Clear | L108: 45994
A109: CL0108 | B109: Bluewater Global Macro Fund Ltd | C109: Investment Fund | D109: Canada | E109: Canada | F109: Fixed Income | G109: Complex | H109: Y | I109: N | J109: Material | K109: Potential Match | L109: 45841
A110: CL0109 | B110: Westmark Logistics Ltd | C110: Corporation | D110: Ireland | E110: Europe | F110: Equities | G110: Simple | H110: Y | I110: N | J110: Minor | K110: Clear | L110: 46267
A111: CL0110 | B111: Stonebridge Holdings Inc. | C111: Corporation | D111: Canada | E111: Canada | F111: Equities | G111: Simple | H111: Y | I111: N | J111: None | K111: Clear | L111: 45643
A112: CL0111 | B112: Stonebridge Opportunities Fund Ltd | C112: Investment Fund | D112: Singapore | E112: APAC | F112: FX | G112: Complex | H112: Y | I112: N | J112: None | K112: Clear | L112: 45313
A113: CL0112 | B113: Crescent Multi-Strategy Fund LP | C113: Investment Fund | D113: Cayman Islands | E113: Offshore | F113: Fixed Income | G113: Complex | H113: Y | I113: N | J113: None | K113: Clear | L113: 45182
A114: CL0113 | B114: Summit Credit Fund Ltd | C114: Investment Fund | D114: United States | E114: US | F114: FX | G114: Simple | H114: Y | I114: N | J114: None | K114: Clear | L114: 46099
A115: CL0114 | B115: Oakridge Legacy Trust | C115: Trust | D115: Canada | E115: Canada | F115: Equities | G115: Complex | H115: Y | I115: N | J115: Material | K115: Clear | L115: 46182
A116: CL0115 | B116: Summit Partners Inc. | C116: Corporation | D116: Canada | E116: Canada | F116: Equities | G116: Simple | H116: Y | I116: N | J116: None | K116: Clear | L116: 45630
A117: CL0116 | B117: Lakeshore Global Macro Fund Ltd | C117: Investment Fund | D117: United States | E117: US | F117: FX | G117: Complex | H117: N | I117: N | J117: None | K117: Clear | L117: 45715
... A122: CL0121 | B122: Fairhaven Asset Management S.à r.l. | C122: Corporation | D122: Luxembourg | E122: Europe | F122: Equities | G122: Simple | H122: Y | I122: N | J122: Material | K122: Clear | L122: 45396
A123: CL0122 | B123: Lakeshore Global LLC | C123: Corporation | D123: United States | E123: US | F123: Fixed Income | G123: Simple | I123: N | J123: None | K123: Clear | L123: 45914
A124: CL0123 | B124: Stonebridge Global Macro Fund Ltd | C124: Investment Fund | D124: British Virgin Islands | E124: Offshore | F124: FX | G124: Complex | H124: Y | I124: N | J124: None | K124: Clear | L124: 45681
A125: CL0124 | B125: Stonebridge Bank LLC | C125: Bank | D125: United States | E125: US | F125: Fixed Income | G125: Simple | H125: Y | I125: N | J125: None | K125: Clear | L125: 45707
A126: CL0125 | B126: Brightwater Partners Ltd | C126: Corporation | D126: United Kingdom | E126: UK | F126: Equities | G126: Simple | H126: Y | I126: N | J126: None | K126: Clear | L126: 45577
A127: CL0126 | B127: Maple Employees Pension Plan | C127: Pension Fund | D127: Canada | E127: Canada | F127: Fixed Income | G127: Simple | H127: Y | I127: N | J127: None | K127: Clear | L127: 44865
A128: CL0127 | B128: Stonebridge Legacy Trust | C128: Trust | D128: United Kingdom | E128: UK | F128: Equities | G128: Complex | H128: N | I128: N | J128: None | K128: Clear | L128: 45147
A129: CL0128 | B129: Aurora Trust Company Inc. | C129: Bank | D129: Canada | E129: Canada | F129: FX | G129: Simple | H129: Y | I129: N | J129: None | K129: Clear | L129: 45443
A130: CL0129 | B130: Brightwater Equity Income Fund LP | C130: Investment Fund | D130: Canada | E130: Canada | F130: Equities | G130: Simple | H130: Y | I130: N | J130: None | K130: Clear | L130: 45791
A131: CL0130 | B131: Aurora Energy Pty Ltd | C131: Corporation | D131: Australia | E131: APAC | F131: Fixed Income | G131: Simple | H131: Y | I131: N | J131: None | K131: Clear | L131: 45442
A132: CL0131 | B132: Fairhaven Opportunities Fund LP | C132: Investment Fund | D132: Japan | E132: APAC | F132: FX | G132: Simple | H132: Y | I132: Y | J132: None | K132: Clear | L132: 45511
A133: CL0132 | B133: Cedar Equity Income Fund LP | C133: Investment Fund | D133: Germany | E133: Europe | F133: FX | G133: Complex | H133: Y | I133: N | J133: None | K133: Clear | L133: 45266
A134: CL0133 | B134: Bluewater Credit Fund Ltd | C134: Investment Fund | D134: Canada | E134: Canada | F134: Fixed Income | G134: Complex | H134: Y | I134: N | J134: None | K134: Clear | L134: 45076
A135: CL0134 | B135: Summit Trust Company Inc. | C135: Bank | D135: Canada | E135: Canada | F135: Fixed Income | G135: Simple | H135: Y | I135: N | J135: None | K135: Clear | L135: 46010
... A164: CL0163 | B164: Kingsway Multi-Strategy Fund Ltd | C164: Investment Fund | D164: United Kingdom | E164: UK | F164: Fixed Income | G164: Simple | H164: Y | I164: N | J164: None | K164: Clear | L164: 45844
A165: CL0164 | B165: Westmark Heritage Trust | C165: Trust | D165: Canada | E165: Canada | F165: Equities | G165: Simple | I165: N | J165: None | K165: Clear | L165: 45595
A166: CL0165 | B166: Highgate Multi-Strategy Fund LP | C166: Investment Fund | D166: United Kingdom | E166: UK | F166: Fixed Income | G166: Complex | H166: Y | I166: N | J166: Minor | K166: Clear | L166: 45616
A167: CL0166 | B167: Granite Advisors Ltd | C167: Corporation | D167: United Kingdom | E167: UK | F167: FX | G167: Simple | H167: Y | I167: N | J167: None | K167: Potential Match | L167: 45293
A168: CL0167 | B168: Meridian Energy Ltd | C168: Corporation | D168: United Kingdom | E168: UK | F168: Equities | G168: Simple | H168: Y | I168: Y | J168: None | K168: Clear | L168: 46062
A169: CL0168 | B169: Kingsway Equity Income Fund LP | C169: Investment Fund | D169: United Kingdom | E169: UK | F169: Fixed Income | G169: Complex | H169: N | I169: N | J169: None | K169: Clear | L169: 45407
A170: CL0169 | B170: Summit Multi-Strategy Fund LP | C170: Investment Fund | D170: Canada | E170: Canada | F170: FX | G170: Simple | H170: Y | I170: N | J170: None | K170: Clear | L170: 46135
A171: CL0170 | B171: Oakridge Multi-Strategy Fund LP | C171: Investment Fund | D171: United States | E171: US | F171: Equities | G171: Complex | H171: Y | I171: N | J171: None | K171: Clear | L171: 45727
A172: CL0171 | B172: Redstone Employees Pension Plan | C172: Pension Fund | D172: Japan | E172: APAC | F172: Fixed Income | G172: Simple | H172: Y | I172: N | J172: None | K172: Clear | L172: 44858
A173: CL0172 | B173: Lakeshore Industries LLC | C173: Corporation | D173: United States | E173: US | F173: FX | G173: Simple | H173: N | I173: N | J173: Material | K173: Clear | L173: 46131
A174: CL0173 | B174: Stonebridge Logistics Inc. | C174: Corporation | D174: Canada | E174: Canada | F174: Fixed Income | G174: Complex | H174: Y | I174: N | J174: None | K174: Clear | L174: 45348
A175: CL0174 | B175: Maple Credit Fund LP | C175: Investment Fund | D175: Canada | E175: Canada | F175: Fixed Income | G175: Complex | H175: Y | I175: N | J175: None | K175: Clear | L175: 45384
A176: CL0175 | B176: Eastbay Global Macro Fund Ltd | C176: Investment Fund | D176: Canada | E176: Canada | F176: Equities | G176: Simple | H176: Y | I176: N | J176: None | K176: Clear | L176: 45765
A177: CL0176 | B177: Cedar Trust Company Ltd | C177: Bank | D177: United Kingdom | E177: UK | F177: Equities | G177: Simple | H177: Y | I177: N | J177: None | K177: Clear | L177: 45331
... A201: CL0200 | B201: Silverline Energy Inc. | C201: Corporation | D201: Canada | E201: Canada | F201: FX | G201: Simple | H201: Y | I201: N | J201: None | K201: Clear | L201: 45652

Sheet Change_Log
A1: Client_ID | B1: Field | C1: Old_Value | D1: New_Value | E1: Date | F1: Reason
A2: CL0003 | B2: Region | C2: Europe | D2: APAC | E2: 46314 | F2: Region did not match country (Japan)
A3: CL0038 | B3: Region | C3: APAC | D3: Europe | E3: 46314 | F3: Region did not match country (Germany)
A4: CL0091 | B4: Region | C4: UK | D4: APAC | E4: 46314 | F4: Region did not match country (Singapore)
A5: CL0120 | B5: Region | C5: US | D5: Europe | E5: 46314 | F5: Region did not match country (France)

Sheet Risk_Scoring
A1: Client_ID | B1: Jurisdiction_Score | C1: Entity_Score | D1: Ownership_Score | E1: UBO_Score | F1: PEP_Score | G1: Media_Score | H1: Total_Score | I1: Sanctions_Flag | J1: Risk_Rating | L1: Jurisdiction | M1: Points
A2: =Client_Master!A2 -> CL0001 | B2: =VLOOKUP(Client_Master!E2,$L$2:$M$7,2,FALSE) -> 0 | C2: =VLOOKUP(Client_Master!C2,$L$10:$M$14,2,FALSE) -> 2 | L2: Canada | M2: 0
A3: =Client_Master!A3 -> CL0002 | B3: =VLOOKUP(Client_Master!E3,$L$2:$M$7,2,FALSE) -> 0 | C3: =VLOOKUP(Client_Master!C3,$L$10:$M$14,2,FALSE) -> 0 | L3: US | M3: 0
A4: =Client_Master!A4 -> CL0003 | B4: =VLOOKUP(Client_Master!E4,$L$2:$M$7,2,FALSE) -> 1 | C4: =VLOOKUP(Client_Master!C4,$L$10:$M$14,2,FALSE) -> 2 | L4: UK | M4: 0
A5: =Client_Master!A5 -> CL0004 | B5: =VLOOKUP(Client_Master!E5,$L$2:$M$7,2,FALSE) -> 0 | C5: =VLOOKUP(Client_Master!C5,$L$10:$M$14,2,FALSE) -> 2 | L5: Europe | M5: 1
A6: =Client_Master!A6 -> CL0005 | B6: =VLOOKUP(Client_Master!E6,$L$2:$M$7,2,FALSE) -> 0 | C6: =VLOOKUP(Client_Master!C6,$L$10:$M$14,2,FALSE) -> 2 | L6: APAC | M6: 1
A7: =Client_Master!A7 -> CL0006 | B7: =VLOOKUP(Client_Master!E7,$L$2:$M$7,2,FALSE) -> 0 | C7: =VLOOKUP(Client_Master!C7,$L$10:$M$14,2,FALSE) -> 0 | L7: Offshore | M7: 3
A8: =Client_Master!A8 -> CL0007 | B8: =VLOOKUP(Client_Master!E8,$L$2:$M$7,2,FALSE) -> 0 | C8: =VLOOKUP(Client_Master!C8,$L$10:$M$14,2,FALSE) -> 1
A9: =Client_Master!A9 -> CL0008 | B9: =VLOOKUP(Client_Master!E9,$L$2:$M$7,2,FALSE) -> 3 | C9: =VLOOKUP(Client_Master!C9,$L$10:$M$14,2,FALSE) -> 2 | L9: Entity_Type | M9: Points
A10: =Client_Master!A10 -> CL0009 | B10: =VLOOKUP(Client_Master!E10,$L$2:$M$7,2,FALSE) -> 1 | C10: =VLOOKUP(Client_Master!C10,$L$10:$M$14,2,FALSE) -> 0 | L10: Bank | M10: 0
A11: =Client_Master!A11 -> CL0010 | B11: =VLOOKUP(Client_Master!E11,$L$2:$M$7,2,FALSE) -> 0 | C11: =VLOOKUP(Client_Master!C11,$L$10:$M$14,2,FALSE) -> 0 | L11: Pension Fund | M11: 0
A12: =Client_Master!A12 -> CL0011 | B12: =VLOOKUP(Client_Master!E12,$L$2:$M$7,2,FALSE) -> 3 | C12: =VLOOKUP(Client_Master!C12,$L$10:$M$14,2,FALSE) -> 2 | L12: Corporation | M12: 1
A13: =Client_Master!A13 -> CL0012 | B13: =VLOOKUP(Client_Master!E13,$L$2:$M$7,2,FALSE) -> 0 | C13: =VLOOKUP(Client_Master!C13,$L$10:$M$14,2,FALSE) -> 1 | L13: Investment Fund | M13: 2
A14: =Client_Master!A14 -> CL0013 | B14: =VLOOKUP(Client_Master!E14,$L$2:$M$7,2,FALSE) -> 0 | C14: =VLOOKUP(Client_Master!C14,$L$10:$M$14,2,FALSE) -> 2 | L14: Trust | M14: 2
A15: =Client_Master!A15 -> CL0014 | B15: =VLOOKUP(Client_Master!E15,$L$2:$M$7,2,FALSE) -> 1 | C15: =VLOOKUP(Client_Master!C15,$L$10:$M$14,2,FALSE) -> 0
A16: =Client_Master!A16 -> CL0015 | B16: =VLOOKUP(Client_Master!E16,$L$2:$M$7,2,FALSE) -> 3 | C16: =VLOOKUP(Client_Master!C16,$L$10:$M$14,2,FALSE) -> 2
A17: =Client_Master!A17 -> CL0016 | B17: =VLOOKUP(Client_Master!E17,$L$2:$M$7,2,FALSE) -> 1 | C17: =VLOOKUP(Client_Master!C17,$L$10:$M$14,2,FALSE) -> 2
A18: =Client_Master!A18 -> CL0017 | B18: =VLOOKUP(Client_Master!E18,$L$2:$M$7,2,FALSE) -> 0 | C18: =VLOOKUP(Client_Master!C18,$L$10:$M$14,2,FALSE) -> 2
A19: =Client_Master!A19 -> CL0018 | B19: =VLOOKUP(Client_Master!E19,$L$2:$M$7,2,FALSE) -> 0 | C19: =VLOOKUP(Client_Master!C19,$L$10:$M$14,2,FALSE) -> 0
A20: =Client_Master!A20 -> CL0019 | B20: =VLOOKUP(Client_Master!E20,$L$2:$M$7,2,FALSE) -> 0 | C20: =VLOOKUP(Client_Master!C20,$L$10:$M$14,2,FALSE) -> 2
A21: =Client_Master!A21 -> CL0020 | B21: =VLOOKUP(Client_Master!E21,$L$2:$M$7,2,FALSE) -> 3 | C21: =VLOOKUP(Client_Master!C21,$L$10:$M$14,2,FALSE) -> 2
A22: =Client_Master!A22 -> CL0021 | B22: =VLOOKUP(Client_Master!E22,$L$2:$M$7,2,FALSE) -> 0 | C22: =VLOOKUP(Client_Master!C22,$L$10:$M$14,2,FALSE) -> 0
A23: =Client_Master!A23 -> CL0022 | B23: =VLOOKUP(Client_Master!E23,$L$2:$M$7,2,FALSE) -> 0 | C23: =VLOOKUP(Client_Master!C23,$L$10:$M$14,2,FALSE) -> 2
A24: =Client_Master!A24 -> CL0023 | B24: =VLOOKUP(Client_Master!E24,$L$2:$M$7,2,FALSE) -> 1 | C24: =VLOOKUP(Client_Master!C24,$L$10:$M$14,2,FALSE) -> 1
A25: =Client_Master!A25 -> CL0024 | B25: =VLOOKUP(Client_Master!E25,$L$2:$M$7,2,FALSE) -> 1 | C25: =VLOOKUP(Client_Master!C25,$L$10:$M$14,2,FALSE) -> 2
A26: =Client_Master!A26 -> CL0025 | B26: =VLOOKUP(Client_Master!E26,$L$2:$M$7,2,FALSE) -> 0 | C26: =VLOOKUP(Client_Master!C26,$L$10:$M$14,2,FALSE) -> 0
... A201: =Client_Master!A201 -> CL0200 | B201: =VLOOKUP(Client_Master!E201,$L$2:$M$7,2,FALSE) -> 0 | C201: =VLOOKUP(Client_Master!C201,$L$10:$M$14,2,FALSE) -> 1

Sheet Refresh_Queue
A1: Built in Step 4

Sheet Document_Tracker
A1: Built in Step 5

Sheet Escalation_Log
A1: Built in Step 6

Sheet QC_Review
A1: Built in Step 7
